{
  "frames": {
    "characters/armored knight/White Armored Knight/PNG/PNG Sequences/Running/Running_001.png": {
      "frame": {
        "x": 0,
        "y": 0,
        "w": 369,
        "h": 621
      },
      "rotated": false,
      "trimmed": true,
      "spriteSourceSize": {
        "x": 277,
        "y": 105,
        "w": 369,
        "h": 621
      },
      "sourceSize": {
        "w": 900,
        "h": 900
      },
      "pivot": {
        "x": 0.5,
        "y": 0.5
      }
    },
    "characters/armored knight/White Armored Knight/PNG/PNG Sequences/Walking/Walking_002.png": {
      "frame": {
        "x": 0,
        "y": 621,
        "w": 369,
        "h": 621
      },
      "rotated": false,
      "trimmed": true,
      "spriteSourceSize": {
        "x": 290,
        "y": 113,
        "w": 369,
        "h": 621
      },
      "sourceSize": {
        "w": 900,
        "h": 900
      },
      "pivot": {
        "x": 0.5,
        "y": 0.5
      }
    },
    "characters/armored knight/White Armored Knight/PNG/PNG Sequences/Walking/Walking_013.png": {
      "frame": {
        "x": 0,
        "y": 1242,
        "w": 369,
        "h": 621
      },
      "rotated": false,
      "trimmed": true,
      "spriteSourceSize": {
        "x": 291,
        "y": 115,
        "w": 369,
        "h": 621
      },
      "sourceSize": {
        "w": 900,
        "h": 900
      },
      "pivot": {
        "x": 0.5,
        "y": 0.5
      }
    },
    "characters/armored knight/White Armored Knight/PNG/PNG Sequences/Slashing/Slashing_002.png": {
      "frame": {
        "x": 369,
        "y": 0,
        "w": 607,
        "h": 620
      },
      "rotated": true,
      "trimmed": true,
      "spriteSourceSize": {
        "x": 269,
        "y": 112,
        "w": 607,
        "h": 620
      },
      "sourceSize": {
        "w": 900,
        "h": 900
      },
      "pivot": {
        "x": 0.5,
        "y": 0.5
      }
    },
    "characters/armored knight/White Armored Knight/PNG/PNG Sequences/Slashing/Slashing_010.png": {
      "frame": {
        "x": 989,
        "y": 0,
        "w": 571,
        "h": 620
      },
      "rotated": true,
      "trimmed": true,
      "spriteSourceSize": {
        "x": 288,
        "y": 112,
        "w": 571,
        "h": 620
      },
      "sourceSize": {
        "w": 900,
        "h": 900
      },
      "pivot": {
        "x": 0.5,
        "y": 0.5
      }
    },
    "characters/elf archer/Archer_2/PNG/PNG Sequences/Run Shooting/0_Archer_Run Shooting_011.png": {
      "frame": {
        "x": 1609,
        "y": 0,
        "w": 439,
        "h": 607
      },
      "rotated": false,
      "trimmed": true,
      "spriteSourceSize": {
        "x": 167,
        "y": 140,
        "w": 439,
        "h": 607
      },
      "sourceSize": {
        "w": 900,
        "h": 900
      },
      "pivot": {
        "x": 0.5,
        "y": 0.5
      }
    },
    "characters/ninja/White Ninja/PNG/PNG Sequences/Slashing/Slashing_003.png": {
      "frame": {
        "x": 989,
        "y": 571,
        "w": 620,
        "h": 546
      },
      "rotated": false,
      "trimmed": true,
      "spriteSourceSize": {
        "x": 268,
        "y": 187,
        "w": 620,
        "h": 546
      },
      "sourceSize": {
        "w": 900,
        "h": 900
      },
      "pivot": {
        "x": 0.5,
        "y": 0.5
      }
    },
    "characters/elf archer/Archer_2/PNG/PNG Sequences/Running/0_Archer_Running_004.png": {
      "frame": {
        "x": 1609,
        "y": 607,
        "w": 439,
        "h": 586
      },
      "rotated": false,
      "trimmed": true,
      "spriteSourceSize": {
        "x": 132,
        "y": 155,
        "w": 439,
        "h": 586
      },
      "sourceSize": {
        "w": 900,
        "h": 900
      },
      "pivot": {
        "x": 0.5,
        "y": 0.5
      }
    },
    "characters/elf archer/Archer_2/PNG/PNG Sequences/Shooting/0_Archer_Shooting_000.png": {
      "frame": {
        "x": 369,
        "y": 607,
        "w": 531,
        "h": 620
      },
      "rotated": true,
      "trimmed": true,
      "spriteSourceSize": {
        "x": 202,
        "y": 132,
        "w": 531,
        "h": 620
      },
      "sourceSize": {
        "w": 900,
        "h": 900
      },
      "pivot": {
        "x": 0.5,
        "y": 0.5
      }
    },
    "characters/elf archer/Archer_2/PNG/PNG Sequences/Shooting in The Air/0_Archer_Shooting in The Air_008.png": {
      "frame": {
        "x": 989,
        "y": 1117,
        "w": 459,
        "h": 620
      },
      "rotated": true,
      "trimmed": true,
      "spriteSourceSize": {
        "x": 168,
        "y": 103,
        "w": 459,
        "h": 620
      },
      "sourceSize": {
        "w": 900,
        "h": 900
      },
      "pivot": {
        "x": 0.5,
        "y": 0.5
      }
    },
    "characters/archer/Archer_2/PNG/PNG Sequences/Throwing in The Air/0_Archer_Throwing in The Air_003.png": {
      "frame": {
        "x": 1609,
        "y": 1193,
        "w": 439,
        "h": 585
      },
      "rotated": false,
      "trimmed": true,
      "spriteSourceSize": {
        "x": 207,
        "y": 132,
        "w": 439,
        "h": 585
      },
      "sourceSize": {
        "w": 900,
        "h": 900
      },
      "pivot": {
        "x": 0.5,
        "y": 0.5
      }
    },
    "characters/elf archer/Archer_2/PNG/PNG Sequences/Dying/0_Archer_Dying_005.png": {
      "frame": {
        "x": 369,
        "y": 1138,
        "w": 424,
        "h": 620
      },
      "rotated": true,
      "trimmed": true,
      "spriteSourceSize": {
        "x": 208,
        "y": 70,
        "w": 424,
        "h": 620
      },
      "sourceSize": {
        "w": 900,
        "h": 900
      },
      "pivot": {
        "x": 0.5,
        "y": 0.5
      }
    },
    "characters/archer/Archer_3/PNG/PNG Sequences/Run Shooting/0_Archer_Run Shooting_009.png": {
      "frame": {
        "x": 369,
        "y": 1562,
        "w": 486,
        "h": 563
      },
      "rotated": true,
      "trimmed": true,
      "spriteSourceSize": {
        "x": 179,
        "y": 176,
        "w": 486,
        "h": 563
      },
      "sourceSize": {
        "w": 900,
        "h": 900
      },
      "pivot": {
        "x": 0.5,
        "y": 0.5
      }
    },
    "characters/archer/Archer_1/PNG/PNG Sequences/Shooting in The Air/0_Archer_Shooting in The Air_007.png": {
      "frame": {
        "x": 932,
        "y": 1576,
        "w": 472,
        "h": 549
      },
      "rotated": true,
      "trimmed": true,
      "spriteSourceSize": {
        "x": 152,
        "y": 174,
        "w": 472,
        "h": 549
      },
      "sourceSize": {
        "w": 900,
        "h": 900
      },
      "pivot": {
        "x": 0.5,
        "y": 0.5
      }
    }
  },
  "meta": {
    "app": "http://free-tex-packer.com",
    "version": "0.6.7",
    "image": "texture-27.png",
    "format": "RGBA8888",
    "size": {
      "w": 2048,
      "h": 2048
    },
    "scale": 1
  }
}